PySide6_VerticalQTabWidget/VerticalQTabWidget.py
PySide6_VerticalQTabWidget/__init__.py
PySide6_VerticalQTabWidget-0.0.3.dist-info/LICENSE
PySide6_VerticalQTabWidget-0.0.3.dist-info/METADATA
PySide6_VerticalQTabWidget-0.0.3.dist-info/WHEEL
PySide6_VerticalQTabWidget-0.0.3.dist-info/top_level.txt
PySide6_VerticalQTabWidget-0.0.3.dist-info/RECORD
