Metadata-Version: 2.1
Name: PySide6-VerticalQTabWidget
Version: 0.0.3
Summary: Vertical QTabWidget for PySide6
Home-page: https://github.com/mauriliogenovese/PySide6_VerticalQTabWidget
Author: Maurilio Genovese
Author-email: mauriliogenovese@gmail.com
License: MIT
License-File: LICENSE
Requires-Dist: PySide6 >=6.4
